lumnisai/__init__.py
lumnisai/async_client.py
lumnisai/client.py
lumnisai/config.py
lumnisai/constants.py
lumnisai/exceptions.py
lumnisai/py.typed
lumnisai/types.py
lumnisai/utils.py
lumnisai/_transport/__init__.py
lumnisai/_transport/http.py
lumnisai/models/__init__.py
lumnisai/models/agent_config.py
lumnisai/models/external_api_keys.py
lumnisai/models/files.py
lumnisai/models/integrations.py
lumnisai/models/mcp_servers.py
lumnisai/models/model_names.py
lumnisai/models/model_preferences.py
lumnisai/models/response.py
lumnisai/models/tenant.py
lumnisai/models/thread.py
lumnisai/models/user.py
lumnisai/resources/__init__.py
lumnisai/resources/base.py
lumnisai/resources/external_api_keys.py
lumnisai/resources/files.py
lumnisai/resources/integrations.py
lumnisai/resources/mcp_servers.py
lumnisai/resources/model_preferences.py
lumnisai/resources/responses.py
lumnisai/resources/tenant.py
lumnisai/resources/threads.py
lumnisai/resources/users.py
lumnisai-0.2.6.dist-info/METADATA
lumnisai-0.2.6.dist-info/WHEEL
lumnisai-0.2.6.dist-info/licenses/LICENSE
lumnisai-0.2.6.dist-info/RECORD
