Metadata-Version: 2.4
Name: lumnisai
Version: 0.2.6
Summary: Agent-oriented SDK for the Lumnis multi-tenant AI platform
Project-URL: Homepage, https://github.com/lumnisai/lumnisai-python
Project-URL: Documentation, https://lumnisai.github.io/lumnisai-python
Project-URL: Issues, https://github.com/lumnisai/lumnisai-python/issues
Project-URL: Source, https://github.com/lumnisai/lumnisai-python
Author-email: Lumnis AI <dev@lumnis.ai>
License: Apache-2.0
License-File: LICENSE
Keywords: agents,ai,multi-tenant,sdk
Classifier: Development Status :: 4 - Beta
Classifier: Intended Audience :: Developers
Classifier: License :: OSI Approved :: Apache Software License
Classifier: Operating System :: OS Independent
Classifier: Programming Language :: Python :: 3
Classifier: Programming Language :: Python :: 3.8
Classifier: Programming Language :: Python :: 3.9
Classifier: Programming Language :: Python :: 3.10
Classifier: Programming Language :: Python :: 3.11
Classifier: Programming Language :: Python :: 3.12
Classifier: Topic :: Software Development :: Libraries :: Python Modules
Requires-Python: >=3.8
Requires-Dist: httpx[http2]
Requires-Dist: pydantic[email]>=2.0.0
Requires-Dist: typing-extensions>=4.0.0; python_version < '3.10'
Provides-Extra: dev
Requires-Dist: black>=23.0.0; extra == 'dev'
Requires-Dist: ipykernel>=6.0.0; extra == 'dev'
Requires-Dist: isort>=5.0.0; extra == 'dev'
Requires-Dist: mypy>=1.0.0; extra == 'dev'
Requires-Dist: pyright>=1.1.300; extra == 'dev'
Requires-Dist: pytest-asyncio>=0.21.0; extra == 'dev'
Requires-Dist: pytest>=7.0.0; extra == 'dev'
Requires-Dist: python-dotenv>=0.19.0; extra == 'dev'
Requires-Dist: respx>=0.20.0; extra == 'dev'
Requires-Dist: ruff>=0.1.0; extra == 'dev'
Provides-Extra: docs
Requires-Dist: mkdocs-material>=9.0.0; extra == 'docs'
Requires-Dist: mkdocstrings[python]>=0.20.0; extra == 'docs'
